[{
  "max": {"PKR": "0.02789", "USD": "2.9248", "AUD": "2.1131", "CHF": "2.8516", "NOK": "0.33778", "RUB": "0.04442", "IRR": "0.00979", "BGN": "1.5935", "RON": "0.70108", "JPY": "2.3925", "code": "28.11.2015.2.37", "GBP": "4.4127", "SAR": "0.77916", "KWD": "9.6532", "CNY": "0.45992", "CAD": "2.1977", "SEK": "0.33658", "DKK": "0.41607", "EUR": "3.0994"},
  "code": "28.11.2015",
  "min": {"PKR": "0.02789", "USD": "2.9248", "AUD": "2.1131", "CHF": "2.8516", "NOK": "0.33778", "RUB": "0.04442", "IRR": "0.00979", "BGN": "1.5935", "RON": "0.70108", "JPY": "2.3925", "code": "28.11.2015.2.37", "GBP": "4.4127", "SAR": "0.77916", "KWD": "9.6532", "CNY": "0.45992", "CAD": "2.1977", "SEK": "0.33658", "DKK": "0.41607", "EUR": "3.0994"}
}]